predictors/__init__.py
predictors/helpers.py
predictors/model_wrappers.py
predictors/services.py
predictors/tests/__init__.py
predictors/tests/test_helpers.py
predictors/tests/test_model_wrappers.py
predictors/tests/test_services.py
reply_ai_predictors-0.0.4.dist-info/LICENSE
reply_ai_predictors-0.0.4.dist-info/METADATA
reply_ai_predictors-0.0.4.dist-info/WHEEL
reply_ai_predictors-0.0.4.dist-info/top_level.txt
reply_ai_predictors-0.0.4.dist-info/RECORD
