Metadata-Version: 2.1
Name: reply-ai-predictors
Version: 0.0.4
Summary: Package for encapsulation of AI models to use in Reply AI services
Home-page: https://github.com/reply-team/reply_ai_predictors
Author: Marianna Diachuk
Author-email: marianna.d@reply.io
Project-URL: Bug Tracker, https://github.com/reply-team/reply_ai_predictors
Classifier: Programming Language :: Python :: 3
Classifier: License :: OSI Approved :: MIT License
Classifier: Operating System :: OS Independent
Requires-Python: >=3.7
License-File: LICENSE
